eil/__init__.py
eil/main.py
eil/py.typed
eil/data/__init__.py
eil/data/stdlibs.yml
eil/tests/test_basics.py
pyeil-0.3.1.dist-info/licenses/LICENSE
pyeil-0.3.1.dist-info/METADATA
pyeil-0.3.1.dist-info/WHEEL
pyeil-0.3.1.dist-info/top_level.txt
pyeil-0.3.1.dist-info/RECORD
