Metadata-Version: 2.4
Name: pyeil
Version: 0.3.1
Summary: Small Python utility to extract imported libraries from source code files in various programming languages using tree-sitter.
Author-email: Eva Maxfield Brown <evamaxfieldbrown@gmail.com>
License: MPLv2 License
Project-URL: Homepage, https://github.com/evamaxfield/py-extract-imported-libraries
Project-URL: Bug Tracker, https://github.com/evamaxfield/py-extract-imported-libraries/issues
Project-URL: Documentation, https://evamaxfield.github.io/py-extract-imported-libraries
Project-URL: User Support, https://github.com/evamaxfield/py-extract-imported-libraries/issues
Classifier: Development Status :: 4 - Beta
Classifier: Natural Language :: English
Classifier: Programming Language :: Python :: 3.12
Classifier: Programming Language :: Python :: 3.13
Classifier: Programming Language :: Python :: 3.14
Requires-Python: >=3.12
License-File: LICENSE
Requires-Dist: pyyaml>=6
Requires-Dist: stdlib-list>=0.12
Requires-Dist: tqdm>=4
Requires-Dist: tree-sitter>=0.20
Requires-Dist: tree-sitter-language-pack>=0.13
Provides-Extra: dev
Requires-Dist: ipython; extra == "dev"
Requires-Dist: jupyterlab; extra == "dev"
Provides-Extra: lint
Requires-Dist: prek>=0.2.29; extra == "lint"
Requires-Dist: ty>=0.0.12; extra == "lint"
Provides-Extra: test
Requires-Dist: pytest>=9; extra == "test"
Dynamic: license-file
